hcnb/Hachi_filter.py
hcnb/__init__.py
hcnb/bayes.py
hcnb/test_for_nb.py
hcnb-0.0.1.dist-info/DESCRIPTION.rst
hcnb-0.0.1.dist-info/METADATA
hcnb-0.0.1.dist-info/RECORD
hcnb-0.0.1.dist-info/WHEEL
hcnb-0.0.1.dist-info/metadata.json
hcnb-0.0.1.dist-info/top_level.txt
